uuid_extension/__init__.py
uuid_extension/models.py
uuid_extension/py.typed
uuid_extension/utils.py
uuid_extension-0.1.0.dist-info/METADATA
uuid_extension-0.1.0.dist-info/WHEEL
uuid_extension-0.1.0.dist-info/licenses/LICENSE
uuid_extension-0.1.0.dist-info/RECORD
