Metadata-Version: 2.4
Name: uuid-extension
Version: 0.1.0
Summary: UUID7 Extension for Python
Author-email: Markus Feiks <pypi.packages@feyx.de>
License-File: LICENSE
Requires-Python: >=3.8
